matlab_mcp/__init__.py
matlab_mcp/engine.py
matlab_mcp/models.py
matlab_mcp/server.py
mseep_matlab_mcp_tools-0.1.2.dist-info/licenses/LICENSE
mseep_matlab_mcp_tools-0.1.2.dist-info/METADATA
mseep_matlab_mcp_tools-0.1.2.dist-info/WHEEL
mseep_matlab_mcp_tools-0.1.2.dist-info/entry_points.txt
mseep_matlab_mcp_tools-0.1.2.dist-info/top_level.txt
mseep_matlab_mcp_tools-0.1.2.dist-info/RECORD
