Metadata-Version: 2.4
Name: mseep-matlab-mcp-tools
Version: 0.1.2
Summary: MCP server for MATLAB integration with Cline
Author-email: mseep <support@skydeck.ai>
License: BSD 3-Clause License
Requires-Python: >=3.10
License-File: LICENSE
Requires-Dist: mcp[cli]>=0.1.0
Requires-Dist: matlabengine
Requires-Dist: pydantic>=2.0.0
Requires-Dist: pillow
Provides-Extra: dev
Requires-Dist: uv>=0.1.0; extra == "dev"
Dynamic: license-file
